jupyterlab_optumi/__init__.py
jupyterlab_optumi/_version.py
jupyterlab_optumi/handlers.py
jupyterlab_optumi-3.17.13.data/data/etc/jupyter/jupyter_notebook_config.d/jupyterlab-optumi.json
jupyterlab_optumi-3.17.13.data/data/etc/jupyter/jupyter_server_config.d/jupyterlab-optumi.json
jupyterlab_optumi-3.17.13.data/data/share/jupyter/labextensions/jupyterlab_optumi/build_log.json
jupyterlab_optumi-3.17.13.data/data/share/jupyter/labextensions/jupyterlab_optumi/package.json
jupyterlab_optumi-3.17.13.data/data/share/jupyter/labextensions/jupyterlab_optumi/static/3afd2153804f0b0a9245.png
jupyterlab_optumi-3.17.13.data/data/share/jupyter/labextensions/jupyterlab_optumi/static/3d718f0e1a245d54d5c6.png
jupyterlab_optumi-3.17.13.data/data/share/jupyter/labextensions/jupyterlab_optumi/static/4fcae9d8e0a982d58335.png
jupyterlab_optumi-3.17.13.data/data/share/jupyter/labextensions/jupyterlab_optumi/static/a65c140afd46feaf7a50.png
jupyterlab_optumi-3.17.13.data/data/share/jupyter/labextensions/jupyterlab_optumi/static/b6a6c95d1dac3a4a97ec.png
jupyterlab_optumi-3.17.13.data/data/share/jupyter/labextensions/jupyterlab_optumi/static/common_lib_index_js-node_modules_moment_locale_sync_recursive_-data_image_png_base64_iVBORw0K-4a59bc.8ca5ddcc0abd6ef00b25.js
jupyterlab_optumi-3.17.13.data/data/share/jupyter/labextensions/jupyterlab_optumi/static/common_lib_index_js-node_modules_moment_locale_sync_recursive_-data_image_png_base64_iVBORw0K-4a59bc.8ca5ddcc0abd6ef00b25.js.map
jupyterlab_optumi-3.17.13.data/data/share/jupyter/labextensions/jupyterlab_optumi/static/d357b210197e542ee1cf.png
jupyterlab_optumi-3.17.13.data/data/share/jupyter/labextensions/jupyterlab_optumi/static/dfcab5ea7af85c992221.png
jupyterlab_optumi-3.17.13.data/data/share/jupyter/labextensions/jupyterlab_optumi/static/fa78693105579f193a0c.png
jupyterlab_optumi-3.17.13.data/data/share/jupyter/labextensions/jupyterlab_optumi/static/fda5f2b53ffcf8ab077e.png
jupyterlab_optumi-3.17.13.dist-info/METADATA
jupyterlab_optumi-3.17.13.dist-info/WHEEL
jupyterlab_optumi-3.17.13.dist-info/licenses/LICENSE
jupyterlab_optumi-3.17.13.dist-info/RECORD
