Metadata-Version: 2.3
Name: jupyterlab-optumi
Version: 3.17.13
Dynamic: Keywords
Summary: Offload Jupyter notebooks from your laptop into the cloud
Project-URL: Homepage, https://optumi.com
Author-email: Optumi Inc Authors <cs@optumi.com>
License: Copyright (C) Optumi Inc - All rights reserved.
License-File: LICENSE
Classifier: Framework :: Jupyter
Classifier: Framework :: Jupyter :: JupyterLab
Classifier: Framework :: Jupyter :: JupyterLab :: 4
Classifier: Framework :: Jupyter :: JupyterLab :: Extensions
Classifier: Framework :: Jupyter :: JupyterLab :: Extensions :: Prebuilt
Classifier: License :: OSI Approved :: BSD License
Classifier: Programming Language :: Python
Classifier: Programming Language :: Python :: 3
Classifier: Programming Language :: Python :: 3.8
Classifier: Programming Language :: Python :: 3.9
Classifier: Programming Language :: Python :: 3.10
Classifier: Programming Language :: Python :: 3.11
Requires-Python: >=3.8
Requires-Dist: cryptography>=3.0
Requires-Dist: jupyter-server<3,>=2.0.1
Requires-Dist: jupyterlab<5,>=4.0.0
Requires-Dist: optumi-core~=3.17.2
